tacotiff/__init__.py
tacotiff/core.py
tacotiff/version.py
tacotiff/drivers/gdal_TACOTIFF.so
tacotiff-0.0.6.dist-info/METADATA
tacotiff-0.0.6.dist-info/WHEEL
tacotiff-0.0.6.dist-info/top_level.txt
tacotiff-0.0.6.dist-info/RECORD
