Metadata-Version: 2.4
Name: tacotiff
Version: 0.0.6
Summary: AI-Optimized GeoTIFF reading with JSON metadata bypass
Author-email: Cesar Aybar <cesar.aybar@uv.es>
License: MIT
Project-URL: Homepage, https://github.com/tacofoundation/tacotiff
Project-URL: Repository, https://github.com/tacofoundation/tacotiff.git
Classifier: Development Status :: 3 - Alpha
Classifier: Intended Audience :: Developers
Classifier: License :: OSI Approved :: MIT License
Classifier: Programming Language :: Python :: 3
Classifier: Programming Language :: Python :: 3.8
Classifier: Programming Language :: Python :: 3.9
Classifier: Programming Language :: Python :: 3.10
Classifier: Programming Language :: Python :: 3.11
Classifier: Topic :: Scientific/Engineering :: GIS
Requires-Python: >=3.8
Requires-Dist: gdal
Requires-Dist: numpy
Provides-Extra: dev
Requires-Dist: pytest; extra == "dev"
Requires-Dist: pytest-cov; extra == "dev"
Requires-Dist: black; extra == "dev"
Requires-Dist: flake8; extra == "dev"
